ragmetrics/__init__.py
ragmetrics/api.py
ragmetrics_pkg-0.1.4.dist-info/LICENSE
ragmetrics_pkg-0.1.4.dist-info/METADATA
ragmetrics_pkg-0.1.4.dist-info/WHEEL
ragmetrics_pkg-0.1.4.dist-info/top_level.txt
ragmetrics_pkg-0.1.4.dist-info/RECORD
