Metadata-Version: 2.1
Name: ragmetrics-pkg
Version: 0.1.4
Summary: A package for integrating RagMetrics with LLM calls
Home-page: https://ragmetrics.ai
Author: ragmetrics
License: UNKNOWN
Project-URL: Homepage, https://ragmetrics.ai
Project-URL: Repository, https://github.com/RagMetrics/ragmetrics-package
Platform: UNKNOWN
Classifier: Programming Language :: Python :: 3.11
Classifier: License :: OSI Approved :: MIT License
Classifier: Operating System :: OS Independent
Requires-Python: >=3.6
License-File: LICENSE
Requires-Dist: requests
